envcontext.py
setup.py
envcontext.egg-info/PKG-INFO
envcontext.egg-info/SOURCES.txt
envcontext.egg-info/dependency_links.txt
envcontext.egg-info/top_level.txt